pdtab/__init__.py
pdtab/core/__init__.py
pdtab/core/immediate.py
pdtab/core/oneway.py
pdtab/core/summarize.py
pdtab/core/twoway.py
pdtab/stats/__init__.py
pdtab/stats/tests.py
pdtab/utils/__init__.py
pdtab/utils/data_processing.py
pdtab/viz/__init__.py
pdtab/viz/plots.py
pdtab-0.1.1.dist-info/licenses/LICENSE
pdtab-0.1.1.dist-info/METADATA
pdtab-0.1.1.dist-info/WHEEL
pdtab-0.1.1.dist-info/top_level.txt
pdtab-0.1.1.dist-info/RECORD
