Metadata-Version: 2.4
Name: pdtab
Version: 0.1.1
Summary: A pandas-based library that replicates Stata's tabulate functionality
Home-page: https://github.com/pdtab/pdtab
Author: pdtab Development Team
Author-email: Bryce Wang <bryce6m@stanford.edu>
License: MIT
Project-URL: Homepage, https://github.com/brycewang-stanford/pdtab
Project-URL: Bug Reports, https://github.com/brycewang-stanford/pdtab/issues
Project-URL: Source, https://github.com/brycewang-stanford/pdtab
Project-URL: Documentation, https://pdtab.readthedocs.io/
Keywords: tabulation,crosstab,statistics,stata,pandas,data analysis
Classifier: Development Status :: 4 - Beta
Classifier: Intended Audience :: Science/Research
Classifier: Intended Audience :: Developers
Classifier: License :: OSI Approved :: MIT License
Classifier: Programming Language :: Python :: 3
Classifier: Programming Language :: Python :: 3.8
Classifier: Programming Language :: Python :: 3.9
Classifier: Programming Language :: Python :: 3.10
Classifier: Programming Language :: Python :: 3.11
Classifier: Programming Language :: Python :: 3.12
Classifier: Programming Language :: Python :: 3.13
Classifier: Topic :: Scientific/Engineering
Classifier: Topic :: Scientific/Engineering :: Information Analysis
Classifier: Operating System :: OS Independent
Requires-Python: >=3.8
License-File: LICENSE
Requires-Dist: pandas>=1.0.0
Requires-Dist: numpy>=1.18.0
Requires-Dist: scipy>=1.4.0
Requires-Dist: matplotlib>=3.0.0
Requires-Dist: seaborn>=0.11.0
Requires-Dist: tabulate>=0.8.0
Provides-Extra: dev
Requires-Dist: pytest>=6.0; extra == "dev"
Requires-Dist: pytest-cov>=2.0; extra == "dev"
Requires-Dist: black>=21.0; extra == "dev"
Requires-Dist: flake8>=3.8; extra == "dev"
Requires-Dist: mypy>=0.800; extra == "dev"
Requires-Dist: pre-commit>=2.0; extra == "dev"
Provides-Extra: docs
Requires-Dist: sphinx>=3.0; extra == "docs"
Requires-Dist: sphinx-rtd-theme>=0.5; extra == "docs"
Requires-Dist: nbsphinx>=0.7; extra == "docs"
Requires-Dist: jupyter>=1.0; extra == "docs"
Dynamic: author
Dynamic: home-page
Dynamic: license-file
Dynamic: requires-python
